proma/__init__.py
proma/__main__.py
proma/proma.py
proma/require.py
tests/TestBase.py
tests/__init__.py
proma-0.2.0.dist-info/AUTHORS.rst
proma-0.2.0.dist-info/LICENSE
proma-0.2.0.dist-info/METADATA
proma-0.2.0.dist-info/WHEEL
proma-0.2.0.dist-info/top_level.txt
proma-0.2.0.dist-info/RECORD
