Metadata-Version: 2.1
Name: proma
Version: 0.2.0
Summary: A set of tools to manipulate a python package without a setup.py
Home-page: https://gitlab.com/ydethe/proma
Author: Yann de The
Author-email: yann@johncloud.fr
License: UNKNOWN
Platform: any
Classifier: Development Status :: 3 - Alpha
Classifier: Intended Audience :: Developers
Classifier: License :: OSI Approved :: MIT License
Classifier: Operating System :: OS Independent
Classifier: Programming Language :: Python
Classifier: Programming Language :: Python :: 3.5
Classifier: Topic :: Software Development :: Libraries :: Python Modules
Requires-Python: >=3.5
